table/__init__.py
table/forms.py
table/models.py
table/tables.py
table/urls.py
table/utils.py
table/views.py
table/widgets.py
table/columns/__init__.py
table/columns/base.py
table/columns/calendarcolumn.py
table/columns/checkboxcolumn.py
table/columns/datetimecolumn.py
table/columns/imagecolumn.py
table/columns/linkcolumn.py
table/columns/sequencecolumn.py
table/static/table/css/datatable.bootstrap.css
table/static/table/fonts/glyphicons-halflings-regular.eot
table/static/table/fonts/glyphicons-halflings-regular.svg
table/static/table/fonts/glyphicons-halflings-regular.ttf
table/static/table/fonts/glyphicons-halflings-regular.woff
table/static/table/images/Sorting icons.psd
table/static/table/images/back_disabled.png
table/static/table/images/back_enabled.png
table/static/table/images/back_enabled_hover.png
table/static/table/images/favicon.ico
table/static/table/images/forward_disabled.png
table/static/table/images/forward_enabled.png
table/static/table/images/forward_enabled_hover.png
table/static/table/images/sort_asc.png
table/static/table/images/sort_asc_disabled.png
table/static/table/images/sort_both.png
table/static/table/images/sort_desc.png
table/static/table/images/sort_desc_disabled.png
table/static/table/js/bootstrap.dataTables.js
table/static/table/js/dataTables.fixedColumns.min.js
table/static/table/js/jquery.browser.min.js
table/static/table/js/jquery.dataTables.min.js
table/templates/table/simple_table.html
table/templates/table/table.html
django4_2_datatable-0.3.3.dist-info/LICENSE
django4_2_datatable-0.3.3.dist-info/METADATA
django4_2_datatable-0.3.3.dist-info/WHEEL
django4_2_datatable-0.3.3.dist-info/top_level.txt
django4_2_datatable-0.3.3.dist-info/RECORD
